Workbook

Sheet Dashboard
B2: BICREA — Portfolio ROI Dashboard
B3: Reporting period: trailing 12 months • Reporting currency: USD • Demo data
B5: Invested capital | D5: Estimated value | F5: Annual NOI | H5: Distributions YTD
B6: =SUM(Holdings!E4:E10) -> 14250000 | D6: =SUM(Holdings!F4:F10) -> 22695000 | F6: =SUM(Holdings!G4:G10) -> 1709900 | H6: =SUM(Distributions!F4:F20) -> 1312600
B9: Holdings Summary
B10: Asset | C10: City | D10: Type | E10: Invested | F10: Est. Value | G10: Annual NOI | H10: Cap Rate | I10: Cash Yield
B11: =Holdings!B4 -> Bayshore Office Plaza | C11: =Holdings!C4 -> Tampa | D11: =Holdings!D4 -> Office | E11: =Holdings!E4 -> 3250000 | F11: =Holdings!F4 -> 5150000 | G11: =Holdings!G4 -> 412000 | H11: =IFERROR(Holdings!G4/Holdings!F4,0) -> 0.08 | I11: =IFERROR(Holdings!G4/Holdings!E4,0) -> 0.12676923
B12: =Holdings!B5 -> Gulf Coast Logistics Park | C12: =Holdings!C5 -> Clearwater | D12: =Holdings!D5 -> Industrial | E12: =Holdings!E5 -> 2800000 | F12: =Holdings!F5 -> 4820000 | G12: =Holdings!G5 -> 365000 | H12: =IFERROR(Holdings!G5/Holdings!F5,0) -> 0.075726141 | I12: =IFERROR(Holdings!G5/Holdings!E5,0) -> 0.13035714
B13: =Holdings!B6 -> Sarasota Marina Retail | C13: =Holdings!C6 -> Sarasota | D13: =Holdings!D6 -> Retail | E13: =Holdings!E6 -> 1950000 | F13: =Holdings!F6 -> 3180000 | G13: =Holdings!G6 -> 214500 | H13: =IFERROR(Holdings!G6/Holdings!F6,0) -> 0.06745283 | I13: =IFERROR(Holdings!G6/Holdings!E6,0) -> 0.11
B14: =Holdings!B7 -> St. Pete Multifamily II | C14: =Holdings!C7 -> St. Pete | D14: =Holdings!D7 -> Multifamily | E14: =Holdings!E7 -> 2400000 | F14: =Holdings!F7 -> 3950000 | G14: =Holdings!G7 -> 298000 | H14: =IFERROR(Holdings!G7/Holdings!F7,0) -> 0.075443038 | I14: =IFERROR(Holdings!G7/Holdings!E7,0) -> 0.12416667
B15: =Holdings!B8 -> Pinellas Self-Storage III | C15: =Holdings!C8 -> Largo | D15: =Holdings!D8 -> Storage | E15: =Holdings!E8 -> 1150000 | F15: =Holdings!F8 -> 1575000 | G15: =Holdings!G8 -> 132400 | H15: =IFERROR(Holdings!G8/Holdings!F8,0) -> 0.084063492 | I15: =IFERROR(Holdings!G8/Holdings!E8,0) -> 0.11513043
B16: =Holdings!B9 -> Tampa Riverwalk Mixed-Use | C16: =Holdings!C9 -> Tampa | D16: =Holdings!D9 -> Mixed-use | E16: =Holdings!E9 -> 1600000 | F16: =Holdings!F9 -> 2400000 | G16: =Holdings!G9 -> 168200 | H16: =IFERROR(Holdings!G9/Holdings!F9,0) -> 0.070083333 | I16: =IFERROR(Holdings!G9/Holdings!E9,0) -> 0.105125
B17: =Holdings!B10 -> Bradenton Medical Office | C17: =Holdings!C10 -> Bradenton | D17: =Holdings!D10 -> Office | E17: =Holdings!E10 -> 1100000 | F17: =Holdings!F10 -> 1620000 | G17: =Holdings!G10 -> 119800 | H17: =IFERROR(Holdings!G10/Holdings!F10,0) -> 0.073950617 | I17: =IFERROR(Holdings!G10/Holdings!E10,0) -> 0.10890909
B18: Portfolio Total | E18: =SUM(E11:E17) -> 14250000 | F18: =SUM(F11:F17) -> 22695000 | G18: =SUM(G11:G17) -> 1709900 | H18: =IFERROR(G18/F18,0) -> 0.075342586 | I18: =IFERROR(G18/E18,0) -> 0.11999298
B20: Demo data — figures are illustrative only.

Sheet Holdings
B2: Holdings — Source Data
B3: Asset | C3: City | D3: Type | E3: Invested ($) | F3: Est. Value ($) | G3: Annual NOI ($) | H3: Acquired
B4: Bayshore Office Plaza | C4: Tampa | D4: Office | E4: 3250000 | F4: 5150000 | G4: 412000 | H4: 2022-08-15
B5: Gulf Coast Logistics Park | C5: Clearwater | D5: Industrial | E5: 2800000 | F5: 4820000 | G5: 365000 | H5: 2021-05-30
B6: Sarasota Marina Retail | C6: Sarasota | D6: Retail | E6: 1950000 | F6: 3180000 | G6: 214500 | H6: 2026-04-22
B7: St. Pete Multifamily II | C7: St. Pete | D7: Multifamily | E7: 2400000 | F7: 3950000 | G7: 298000 | H7: 2023-11-08
B8: Pinellas Self-Storage III | C8: Largo | D8: Storage | E8: 1150000 | F8: 1575000 | G8: 132400 | H8: 2026-03-12
B9: Tampa Riverwalk Mixed-Use | C9: Tampa | D9: Mixed-use | E9: 1600000 | F9: 2400000 | G9: 168200 | H9: 2024-09-19
B10: Bradenton Medical Office | C10: Bradenton | D10: Office | E10: 1100000 | F10: 1620000 | G10: 119800 | H10: 2025-02-04
B11: Total | E11: =SUM(E4:E10) -> 14250000 | F11: =SUM(F4:F10) -> 22695000 | G11: =SUM(G4:G10) -> 1709900

Sheet Distributions
B2: Distributions Log (YTD 2026)
B3: Date | C3: Asset | D3: Type | E3: Notes | F3: Amount ($)
B4: 2026-01-30 | C4: Bayshore Office Plaza | D4: Operating | E4: Q4 2025 distribution | F4: 98400
B5: 2026-01-30 | C5: Gulf Coast Logistics Park | D5: Operating | E5: Q4 2025 distribution | F5: 86200
B6: 2026-02-15 | C6: St. Pete Multifamily II | D6: Operating | E6: Monthly cash flow | F6: 24500
B7: 2026-03-15 | C7: St. Pete Multifamily II | D7: Operating | E7: Monthly cash flow | F7: 25100
B8: 2026-04-15 | C8: St. Pete Multifamily II | D8: Operating | E8: Monthly cash flow | F8: 25600
B9: 2026-05-05 | C9: Bayshore Office Plaza | D9: Operating | E9: Q1 2026 distribution | F9: 104200
B10: 2026-05-05 | C10: St. Pete Multifamily II | D10: Operating | E10: Q1 reconciliation true-up | F10: 78600
B11: 2026-06-12 | C11: Sarasota Marina Retail | D11: Refinance | E11: Net refinance proceeds | F11: 145500
B12: 2026-06-30 | C12: Pinellas Self-Storage III | D12: Pref. return | E12: Initial preferred return | F12: 38000
B13: 2026-06-30 | C13: Bradenton Medical Office | D13: Operating | E13: Q2 2026 distribution | F13: 30200
B14: Total YTD | F14: =SUM(F4:F13) -> 656300

Sheet Quarterly
B2: Quarterly Performance
B3: Quarter | C3: Portfolio Value | D3: NOI | E3: Distributions | F3: Trailing Cash Yield
B4: Q3 2025 | C4: 14820000 | D4: 1530000 | E4: 248400 | F4: =IFERROR(E4/C4,0) -> 0.016761134
B5: Q4 2025 | C5: 15240000 | D5: 1582000 | E5: 261800 | F5: =IFERROR(E5/C5,0) -> 0.017178478
B6: Q1 2026 | C6: 15820000 | D6: 1648000 | E6: 284500 | F6: =IFERROR(E6/C6,0) -> 0.017983565
B7: Q2 2026 | C7: 16475000 | D7: 1710000 | E7: 327800 | F7: =IFERROR(E7/C7,0) -> 0.019896813

Sheet Assumptions
B2: Modeling Assumptions
B4: Hold period | C4: 7 years | D4: Standard BICREA underwriting horizon
B5: Target IRR (levered) | C5: 14.0% | D5: Risk-adjusted target across portfolio
B6: Target equity multiple | C6: 1.85x | D6: Across full hold period
B7: Annual rent growth | C7: 3.0% | D7: Demo assumption — Florida Gulf Coast
B8: Exit cap rate spread | C8: +50 bps | D8: Versus current market
B9: Vacancy / collection loss | C9: 5.0% | D9: Stabilized assumption
B10: Reporting currency | C10: USD
B12: Color key: blue = input, black = formula, green = link to other sheet.
